ttcli/__init__.py
ttcli/app.py
ttcli/option.py
ttcli/order.py
ttcli/plot.py
ttcli/portfolio.py
ttcli/trade.py
ttcli/utils.py
ttcli/watchlist.py
ttcli/data/__init__.py
ttcli/data/ttcli.cfg
tastytrade_cli-1.0.1.dist-info/METADATA
tastytrade_cli-1.0.1.dist-info/WHEEL
tastytrade_cli-1.0.1.dist-info/entry_points.txt
tastytrade_cli-1.0.1.dist-info/licenses/LICENSE
tastytrade_cli-1.0.1.dist-info/RECORD
