Metadata-Version: 2.4
Name: tastytrade-cli
Version: 1.0.1
Summary: An easy-to-use command line interface for Tastytrade!
Project-URL: Homepage, https://github.com/tastyware/tastytrade-cli
Project-URL: Funding, https://github.com/sponsors/tastyware
Project-URL: Source, https://github.com/tastyware/tastytrade-cli
Project-URL: Changelog, https://github.com/tastyware/tastytrade-cli/releases
Author-email: Graeme Holliday <graeme@tastyware.dev>
License: MIT License
License-File: LICENSE
Classifier: Development Status :: 5 - Production/Stable
Classifier: Environment :: Console
Classifier: Intended Audience :: Developers
Classifier: Intended Audience :: Financial and Insurance Industry
Classifier: Intended Audience :: Information Technology
Classifier: License :: OSI Approved :: MIT License
Classifier: Operating System :: MacOS :: MacOS X
Classifier: Operating System :: Microsoft :: Windows
Classifier: Operating System :: POSIX :: Linux
Classifier: Operating System :: Unix
Classifier: Programming Language :: Python
Classifier: Programming Language :: Python :: 3
Classifier: Programming Language :: Python :: 3 :: Only
Classifier: Programming Language :: Python :: 3.10
Classifier: Programming Language :: Python :: 3.11
Classifier: Programming Language :: Python :: 3.12
Classifier: Programming Language :: Python :: 3.13
Classifier: Programming Language :: Python :: 3.14
Classifier: Topic :: Internet :: WWW/HTTP
Classifier: Topic :: Software Development :: Libraries :: Python Modules
Requires-Python: >=3.10
Requires-Dist: anyio>=4.6.3
Requires-Dist: py-gnuplot>=1.3
Requires-Dist: rich>=13.8.1
Requires-Dist: tastytrade>=11.0.1
Requires-Dist: typer>=0.15.3
Requires-Dist: yaspin>=3.1.0
